scselpy/__init__.py
scselpy/__main__.py
scselpy/call_main.py
scselpy/config.py
scselpy/version.py
scselpy/version.txt
scselpy/AnndataTestObj/_CreateAnndataObj.py
scselpy/AnndataTestObj/__init__.py
scselpy/Rename_annotation/_GenerateDict.py
scselpy/Rename_annotation/_RenameAnno.py
scselpy/Rename_annotation/__init__.py
scselpy/plotting/__init__.py
scselpy/plotting/_scselpy.py
scselpy/tests/REMAP_val.txt
scselpy/tests/REMAP_val2.txt
scselpy/tests/REMAP_val3.txt
scselpy/tests/__init__.py
scselpy/tests/scselpy_tests.py
scselpy/tests/utils.py
scselpy/tools/__init__.py
scselpy/tools/_calculate_stats.py
scselpy-1.1.7.dist-info/WHEEL
scselpy-1.1.7.dist-info/METADATA
scselpy-1.1.7.dist-info/RECORD
