Metadata-Version: 2.1
Name: scselpy
Version: 1.1.7
Summary: A tool to select cells on scanpy-based scRNA-seq analysis pipelines.
Author: Mark Dedden
Requires-Python: >=3.7
Classifier: Environment :: Console
Classifier: Framework :: Jupyter
Classifier: Natural Language :: English
Classifier: Operating System :: Microsoft :: Windows
Classifier: Operating System :: POSIX :: Linux
Classifier: Programming Language :: Python :: 3.7
Classifier: Programming Language :: Python :: 3.8
Classifier: Programming Language :: Python :: 3.9
Classifier: Topic :: Scientific/Engineering :: Bio-Informatics
Requires-Dist: scanpy >= 1.6
Requires-Dist: anndata>=0.7.6
Requires-Dist: numpy>=1.17.0
Requires-Dist: matplotlib>=3.4
